friendlylog/__init__.py
friendlylog/colored_logger.py
friendlylog/constants.py
friendlylog/simple_logger.py
friendlylog/utils.py
friendlylog-1.0.2.dist-info/LICENSE
friendlylog-1.0.2.dist-info/METADATA
friendlylog-1.0.2.dist-info/WHEEL
friendlylog-1.0.2.dist-info/top_level.txt
friendlylog-1.0.2.dist-info/RECORD
