Metadata-Version: 2.1
Name: friendlylog
Version: 1.0.2
Summary: Python logging for humans: colorful, clean interface, straightforward usage, simply friendly log.
Home-page: https://github.com/SebiSebi/friendlylog
Author: sebisebi
Author-email: gpirtoaca@gmail.com
License: Apache 2.0
Platform: UNKNOWN
Classifier: Programming Language :: Python :: 3
Classifier: Programming Language :: Python :: 2
Classifier: License :: OSI Approved :: Apache Software License
Classifier: Operating System :: OS Independent
Classifier: Topic :: Scientific/Engineering
Classifier: Topic :: Software Development :: Libraries :: Python Modules
Classifier: Development Status :: 5 - Production/Stable
Classifier: Topic :: System :: Logging
